{
  "self_Heal_Framework": [
    {
      "run_id": "24308003553",
      "processed_at": "2026-04-12T14:06:25.428428"
    },
    {
      "run_id": "24348158341",
      "processed_at": "2026-04-13T14:57:52.831364"
    },
    {
      "run_id": "24404126529",
      "processed_at": "2026-04-14T14:57:57.698126"
    },
    {
      "run_id": "24459267993",
      "processed_at": "2026-04-15T14:51:25.530214"
    },
    {
      "run_id": "24515433864",
      "processed_at": "2026-04-16T15:09:28.153160"
    },
    {
      "run_id": "24569129670",
      "processed_at": "2026-04-17T14:38:06.937287"
    },
    {
      "run_id": "24605889021",
      "processed_at": "2026-04-18T14:08:25.326590"
    }
  ],
  "adaptive-api-framework": [
    {
      "run_id": "24307985403",
      "processed_at": "2026-04-12T14:06:26.547847"
    },
    {
      "run_id": "24348116137",
      "processed_at": "2026-04-13T14:57:55.173325"
    },
    {
      "run_id": "24404100198",
      "processed_at": "2026-04-14T14:57:59.975141"
    },
    {
      "run_id": "24459245447",
      "processed_at": "2026-04-15T14:51:27.741513"
    },
    {
      "run_id": "24515414272",
      "processed_at": "2026-04-16T15:09:30.763477"
    },
    {
      "run_id": "24569062672",
      "processed_at": "2026-04-17T14:38:09.133235"
    },
    {
      "run_id": "24605875183",
      "processed_at": "2026-04-18T14:08:27.298486"
    }
  ],
  "automation-framework-playwright": [
    {
      "run_id": "24307985435",
      "processed_at": "2026-04-12T14:06:27.682385"
    },
    {
      "run_id": "24348115602",
      "processed_at": "2026-04-13T14:57:57.870125"
    },
    {
      "run_id": "24404099950",
      "processed_at": "2026-04-14T14:58:02.578897"
    },
    {
      "run_id": "24459244941",
      "processed_at": "2026-04-15T14:51:29.947207"
    },
    {
      "run_id": "24515412905",
      "processed_at": "2026-04-16T15:09:33.531451"
    },
    {
      "run_id": "24569062548",
      "processed_at": "2026-04-17T14:38:11.380656"
    },
    {
      "run_id": "24605875189",
      "processed_at": "2026-04-18T14:08:29.232043"
    }
  ]
}